midiviz/__init__.py
midiviz/themes.py
midiviz/visualizer.py
midiviz/static/main.js
midiviz-1.3.dist-info/licenses/LICENSE
midiviz-1.3.dist-info/METADATA
midiviz-1.3.dist-info/WHEEL
midiviz-1.3.dist-info/top_level.txt
midiviz-1.3.dist-info/RECORD
