Metadata-Version: 2.4
Name: midiviz
Version: 1.3
Summary: An interactive MIDI visualization tool for Jupyter Notebooks.
Author-email: Xiugapurin <jason32567810@gmail.com>
License: MIT
Project-URL: Homepage, https://github.com/Xiugapurin/midiviz
Classifier: Programming Language :: Python :: 3
Classifier: License :: OSI Approved :: MIT License
Classifier: Operating System :: OS Independent
Classifier: Framework :: Jupyter
Classifier: Topic :: Multimedia :: Sound/Audio :: MIDI
Requires-Python: >=3.8
License-File: LICENSE
Requires-Dist: pretty_midi
Requires-Dist: midi2audio
Requires-Dist: ipython
Dynamic: license-file
